raw_docx/__info__.py
raw_docx/__init__.py
raw_docx/raw_bookmark_end.py
raw_docx/raw_bookmark_start.py
raw_docx/raw_document.py
raw_docx/raw_docx.py
raw_docx/raw_image.py
raw_docx/raw_list.py
raw_docx/raw_list_item.py
raw_docx/raw_paragraph.py
raw_docx/raw_run.py
raw_docx/raw_section.py
raw_docx/raw_simple_field.py
raw_docx/raw_table.py
raw_docx/raw_table_cell.py
raw_docx/raw_table_row.py
raw_docx/docx/__init__.py
raw_docx/docx/docx_paragraph.py
raw_docx/docx/docx_table.py
raw_docx-0.11.0.dist-info/licenses/LICENSE
raw_docx-0.11.0.dist-info/METADATA
raw_docx-0.11.0.dist-info/WHEEL
raw_docx-0.11.0.dist-info/top_level.txt
raw_docx-0.11.0.dist-info/RECORD
